LICENSE
MANIFEST.in
README.rst
setup.py
bryl/__init__.py
bryl.egg-info/PKG-INFO
bryl.egg-info/SOURCES.txt
bryl.egg-info/dependency_links.txt
bryl.egg-info/requires.txt
bryl.egg-info/top_level.txt