Metadata-Version: 1.1
Name: bryl
Version: 0.1.0
Summary: .
Home-page: https://github.com/balanced/bryl/
Author: Balanced
Author-email: dev+bryl@balancedpayments.com
License: Copyright (c) 2014 Balanced.
